{
  "name": "UpdateGtmAccessStrategy",
  "protocol": "HTTPS|HTTP",
  "method": "POST|GET",
  "path": "/",
  "timeout": 10000,
  "reqFormat": {
    "RegionId": {
      "name": "RegionId",
      "type": "String",
      "position": "Query",
      "required": false
    },
    "StrategyId": {
      "name": "StrategyId",
      "type": "String",
      "position": "Query",
      "checkBlank": "false",
      "visibility": "Public",
      "required": true,
      "docRequired": true
    },
    "Lang": {
      "name": "Lang",
      "type": "String",
      "position": "Query",
      "checkBlank": "false",
      "visibility": "Public",
      "required": false,
      "docRequired": false
    },
    "UserClientIp": {
      "name": "UserClientIp",
      "type": "String",
      "position": "Query",
      "checkBlank": "false",
      "visibility": "Private",
      "required": false,
      "docRequired": false
    },
    "StrategyName": {
      "name": "StrategyName",
      "type": "String",
      "position": "Query",
      "checkBlank": "false",
      "visibility": "Public",
      "required": false,
      "docRequired": false
    },
    "DefaultAddrPoolId": {
      "name": "DefaultAddrPoolId",
      "type": "String",
      "position": "Query",
      "checkBlank": "false",
      "visibility": "Public",
      "required": false,
      "docRequired": false
    },
    "FailoverAddrPoolId": {
      "name": "FailoverAddrPoolId",
      "type": "String",
      "position": "Query",
      "checkBlank": "false",
      "visibility": "Public",
      "required": false,
      "docRequired": false
    },
    "AccessLines": {
      "name": "AccessLines",
      "type": "String",
      "position": "Query",
      "checkBlank": "false",
      "visibility": "Public",
      "required": false,
      "docRequired": false
    }
  },
  "res": {}
}