{"summary":"查看其他数据源详情。","path":"/v2/openapi/instances/{instanceId}/extra-data-sources/{type}/{dataSourceId}","methods":["get"],"schemes":["http","https"],"security":[{"AK":[]}],"consumes":["application/json"],"produces":["application/json"],"deprecated":false,"systemTags":{"operationType":"get","abilityTreeCode":"117108","abilityTreeNodes":["FEATUREairecXPRU1W"]},"parameters":[{"name":"instanceId","in":"path","schema":{"description":"实例ID","type":"string","required":true,"example":"airec-test","title":"A short description of struct"}},{"name":"type","in":"path","schema":{"description":"数据源类型\nUserCustomDataSource\nItemCustomDataSource\nBehaviorCustomDataSource\nSampleCustomDataSource","type":"string","required":true,"example":"UserCustomDataSource","title":"数据源类型"}},{"name":"dataSourceId","in":"path","schema":{"description":"数据源ID","type":"string","required":true,"example":"123","title":"数据源id"}}],"responses":{"200":{"schema":{"title":"Schema of Response","type":"object","properties":{"requestId":{"title":"Id of the request","type":"string","example":"8B90B646-1678-41A3-B23F-EAC6587B0E48"},"result":{"$ref":"#/components/schemas/ExtraDataSource"}}}}},"responseDemo":"[{\"type\":\"json\",\"example\":\"{}\",\"errorExample\":\"\"},{\"type\":\"xml\",\"example\":\"<result>\\n    <type>UserCustomDataSource</type>\\n    <meta>\\n        <metaType>ExtraDataSource</metaType>\\n        <projectName>project_name</projectName>\\n        <tableName>table</tableName>\\n        <type>ODPS</type>\\n        <updateFrequency>86400</updateFrequency>\\n        <internal>false</internal>\\n    </meta>\\n    <status>Online</status>\\n    <gmtCreate>2021-11-30T11:53:05.000Z</gmtCreate>\\n    <gmtModified>2021-11-30T11:53:05.000Z</gmtModified>\\n    <dataSourceId>cd4bb4b3-1e54-4dbb-a178-e58dac4035a5</dataSourceId>\\n</result>\\n<requestId>90D6B8F5-FE97-4509-9AAB-367836C51818</requestId>\",\"errorExample\":\"\"}]","title":"查看其他数据源详情","requestParamsDescription":" ","responseParamsDescription":" ","extraInfo":" "}