{
  "name": "QueryTaskList",
  "protocol": "HTTPS|HTTP",
  "method": "POST|GET",
  "path": "/",
  "timeout": 10000,
  "reqFormat": {
    "RegionId": {
      "name": "RegionId",
      "type": "String",
      "position": "Query",
      "required": false
    },
    "PageNum": {
      "name": "PageNum",
      "type": "Integer",
      "position": "Query",
      "checkBlank": "false",
      "visibility": "Public",
      "required": true,
      "docRequired": true
    },
    "PageSize": {
      "name": "PageSize",
      "type": "Integer",
      "position": "Query",
      "checkBlank": "false",
      "visibility": "Public",
      "required": true,
      "docRequired": true
    },
    "UserClientIp": {
      "name": "UserClientIp",
      "type": "String",
      "position": "Query",
      "checkBlank": "false",
      "visibility": "Public",
      "required": false,
      "docRequired": false
    },
    "Lang": {
      "name": "Lang",
      "type": "String",
      "position": "Query",
      "checkBlank": "false",
      "visibility": "Public",
      "required": false,
      "docRequired": false
    },
    "BeginCreateTime": {
      "name": "BeginCreateTime",
      "type": "Long",
      "position": "Query",
      "checkBlank": "false",
      "visibility": "Public",
      "required": false,
      "docRequired": false
    },
    "EndCreateTime": {
      "name": "EndCreateTime",
      "type": "Long",
      "position": "Query",
      "checkBlank": "false",
      "visibility": "Public",
      "required": false,
      "docRequired": false
    }
  },
  "res": {}
}