{"summary":"列举实体和权益包关联，可用于获取用户绑定的权益包列表。","path":"/v2/benefit/identity_to_benefit_pkg_mapping/list","methods":["post"],"schemes":["https","http"],"tags":["api"],"security":[{"AK":[]},{"BearerToken":[]}],"consumes":["application/json"],"produces":["application/json"],"deprecated":false,"systemTags":{},"parameters":[{"name":"domain_id","in":"host","schema":{"type":"string","required":true}},{"name":"body","in":"body","style":"json","schema":{"description":"请求体参数","type":"object","properties":{"identity_type":{"description":"实体的类型\n管理用户权益，传user","type":"string","required":true,"example":"user","enum":["user"]},"identity_id":{"description":"实体的唯一标识\n\n管理用户权益时，传user_id","type":"string","required":true,"example":"user123"},"include_expired":{"description":"是否返回已经超期的权益包，默认为false","type":"boolean","required":false,"example":"false"}},"required":false}}],"responses":{"200":{"schema":{"type":"object","properties":{"items":{"description":"实体绑定的权益包信息列表","type":"array","items":{"description":"实体绑定的权益包信息","$ref":"#/components/schemas/IdentityToBenefitPkgMapping"}}}}}},"responseDemo":"[{\"errorExample\":\"\",\"example\":\"{\\n  \\\"items\\\": [\\n    {\\n      \\\"identity_type\\\": \\\"\\\",\\n      \\\"identity_id\\\": \\\"\\\",\\n      \\\"benefit_pkg_owner_id\\\": \\\"\\\",\\n      \\\"benefit_pkg_id\\\": \\\"\\\",\\n      \\\"benefit_pkg_type\\\": \\\"\\\",\\n      \\\"benefit_pkg_name\\\": \\\"\\\",\\n      \\\"benefit_pkg_priority\\\": 0,\\n      \\\"benefit_pkg_computation_rule\\\": \\\"\\\",\\n      \\\"delivery_info_list\\\": [\\n        {\\n          \\\"amount\\\": 0,\\n          \\\"is_permanent\\\": true,\\n          \\\"expire_time\\\": \\\"\\\",\\n          \\\"created_at\\\": \\\"\\\"\\n        }\\n      ],\\n      \\\"created_at\\\": \\\"\\\",\\n      \\\"updated_at\\\": \\\"\\\"\\n    }\\n  ]\\n}\",\"type\":\"json\"}]","title":"列举实体和权益包关联"}