{"summary":"删除人脸分组中的文件。","path":"/v2/albums/unassign_facegroup_item","methods":["post"],"schemes":["https"],"tags":["api"],"security":[{"BearerToken":[]},{"AK":[]}],"consumes":["application/json"],"produces":["application/json"],"operationType":"write","deprecated":false,"parameters":[{"name":"domain_id","in":"host","schema":{"type":"string","required":true}},{"name":"body","in":"body","style":"json","schema":{"description":"请求体参数。","type":"object","properties":{"drive_id":{"description":"空间id","type":"string","required":true,"example":"123"},"face_group_id":{"description":"人脸分组 id","type":"string","required":true,"example":"Cluster-abc"},"file_id":{"description":"需要被移除人脸分组的文件id","type":"string","required":true,"example":"abcd"}},"required":false}}],"responses":{"204":{}},"responseDemo":"[{\"errorExample\":\"\",\"example\":\"{}\",\"type\":\"json\"}]","title":"删除人脸分组文件"}