{"summary":"删除升级计划。","path":"/escalationPlan/delete","methods":["post"],"schemes":["http","https"],"security":[{"AK":[]}],"consumes":["application/json"],"produces":["application/json"],"deprecated":false,"parameters":[{"name":"body","in":"body","style":"json","schema":{"title":"A short description of struct","description":"A short description of struct","type":"object","properties":{"escalationPlanId":{"title":"升级计划ID","description":"升级计划ID","type":"integer","format":"int64","required":true,"example":"234534"},"clientToken":{"title":"clientToken","description":"幂等标识","type":"string","required":false,"example":"A5A1FEAE-9C47-011C-9C73-A376BC2REQUEST"}},"required":false}}],"responses":{"200":{"schema":{"title":"Schema of Response","description":"Schema of Response","type":"object","properties":{"requestId":{"title":"Id of the request","description":"Id of the request","type":"string","example":"A5A1FEAE-9C47-011C-9C73-A376BC21925D"}}}}},"errorCodes":{"404":[{"errorCode":"EscalationPlanNotExists","errorMessage":"The specified escalation plan does not exist."}]},"responseDemo":"[{\"type\":\"json\",\"example\":\"{\\n  \\\"requestId\\\": \\\"A5A1FEAE-9C47-011C-9C73-A376BC21925D\\\"\\n}\",\"errorExample\":\"\"},{\"type\":\"xml\",\"example\":\"<DeleteEscalationPlanResponse>\\n    <requestId>A5A1FEAE-9C47-011C-9C73-A376BC21925D</requestId>\\n</DeleteEscalationPlanResponse>\",\"errorExample\":\"\"}]","title":"删除升级计划"}