{"methods":["post","get"],"schemes":["http","https"],"security":[{"AK":[]}],"operationType":"read","deprecated":false,"systemTags":{"operationType":"update"},"parameters":[{"name":"Status","in":"query","schema":{"description":"设置近源流量压制的状态。取值：\n\n- **do**：表示开启近源流量压制。\n- **undo**：表示关闭近源流量压制。","type":"string","required":true,"example":"do"}},{"name":"Duration","in":"query","schema":{"description":"要封禁的时长。取值范围：**15**~**43200**，单位：分钟。\n\n> **Status**为**do**（表示开启近源流量压制）时，该参数必选。","type":"integer","format":"int32","required":false,"example":"60"}},{"name":"InstanceId","in":"query","schema":{"description":"要操作的DDoS高防（新BGP）实例的ID。\n\n> 您可以调用[DescribeInstanceIds](~~157459~~)查询所有DDoS高防实例的ID信息。","type":"string","required":true,"example":"ddoscoo-cn-mp91j1ao****"}},{"name":"Lines","in":"query","style":"repeatList","schema":{"description":"要封禁的线路列表。","type":"array","items":{"description":"要设置的线路。取值：\n- **ct**：表示海外电信线路。\n- **cut**：表示海外联通线路。","type":"string","required":false,"example":"ct"},"required":true,"example":"ct","maxItems":20}}],"responses":{"200":{"schema":{"type":"object","properties":{"RequestId":{"description":"本次请求的ID。","type":"string","example":"C33EB3D5-AF96-43CA-9C7E-37A81BC06A1E"}}}}},"responseDemo":"[{\"type\":\"json\",\"example\":\"{\\n  \\\"RequestId\\\": \\\"C33EB3D5-AF96-43CA-9C7E-37A81BC06A1E\\\"\\n}\",\"errorExample\":\"\"},{\"type\":\"xml\",\"example\":\"<ModifyBlockStatusResponse>\\n    <RequestId>C33EB3D5-AF96-43CA-9C7E-37A81BC06A1E</RequestId>\\n</ModifyBlockStatusResponse>\",\"errorExample\":\"\"}]","title":"设置实例近源流量压制","summary":"设置DDoS高防（中国内地）实例的近源流量压制。","description":"> 该接口仅适用于DDoS高防（中国内地）服务。","requestParamsDescription":"调用API时，除了本文中该API的请求参数，还需加入阿里云API公共请求参数。公共请求参数的详细介绍，请参见[公共参数](~~157269~~)。\n\n调用API的请求格式，请参见本文**示例**中的请求示例。","responseParamsDescription":" ","extraInfo":" "}