{"summary":"获取当前的租户列表。","methods":["post","get"],"schemes":["http","https"],"security":[{"AK":[]}],"operationType":"read","deprecated":false,"systemTags":{"operationType":"list","riskType":"none","chargeType":"free"},"parameters":[{"name":"Tid","in":"query","schema":{"description":"租户ID，可通过调用接口[GetUserActiveTenant](~~198073~~)获取该参数的值。","type":"integer","format":"int64","required":false,"maximum":"9223372036854775807","minimum":"1","example":"3***"}}],"responses":{"200":{"schema":{"type":"object","properties":{"RequestId":{"description":"请求ID。","type":"string","example":"C478D9DA-3615-50F6-A2BC-7855AD65****"},"TenantList":{"description":"租户信息列表。","type":"array","items":{"description":"租户信息列表。","type":"object","properties":{"Status":{"description":"租户状态，返回值如下：\n\n- **ACTIVE**：活跃，表示用户正处于当前租户下。\n- **IN_ACTIVE**：非活跃。","type":"string","example":"ACTIVE"},"Tid":{"description":"租户ID。","type":"integer","format":"int64","example":"3***"},"TenantName":{"description":"租户名称。","type":"string","example":"test_name"}}}},"ErrorCode":{"description":"错误码。","type":"string","example":"TenantNotExist"},"ErrorMessage":{"description":"错误信息。","type":"string","example":"The specified tenant does not exist."},"Success":{"description":"请求是否成功，返回值如下：\n- **true**：请求成功\n- **false**：请求失败","type":"boolean","example":"true"}}}}},"responseDemo":"[{\"type\":\"json\",\"example\":\"{\\n  \\\"RequestId\\\": \\\"C478D9DA-3615-50F6-A2BC-7855AD65****\\\",\\n  \\\"TenantList\\\": [\\n    {\\n      \\\"Status\\\": \\\"ACTIVE\\\",\\n      \\\"Tid\\\": 0,\\n      \\\"TenantName\\\": \\\"test_name\\\"\\n    }\\n  ],\\n  \\\"ErrorCode\\\": \\\"TenantNotExist\\\",\\n  \\\"ErrorMessage\\\": \\\"The specified tenant does not exist.\\\",\\n  \\\"Success\\\": true\\n}\",\"errorExample\":\"\"},{\"type\":\"xml\",\"example\":\"<ListUserTenantsResponse>\\n    <RequestId>C478D9DA-3615-50F6-A2BC-7855AD65****</RequestId>\\n    <TenantList>\\n        <Status>ACTIVE</Status>\\n        <TenantName>test_name</TenantName>\\n        <Tid>3***</Tid>\\n    </TenantList>\\n    <Success>true</Success>\\n</ListUserTenantsResponse>\",\"errorExample\":\"\"}]","title":"获取当前的租户列表"}