{"methods":["post","get"],"schemes":["https"],"security":[{"AK":[]}],"operationType":"readAndWrite","systemTags":{"operationType":"delete"},"parameters":[{"name":"VaultId","in":"query","schema":{"description":"备份仓库ID。","type":"string","required":false,"example":"v-0008n2q******ax3"}},{"name":"ClientId","in":"query","schema":{"description":"备份客户端ID。","type":"string","required":true,"example":"c-000iuqo******zi3rn"}},{"name":"ResourceGroupId","in":"query","schema":{"description":"资源组ID。","type":"string","required":false,"example":"rg-acfm3erpwweavki"}}],"responses":{"200":{"schema":{"type":"object","properties":{"Code":{"description":"返回码，200表示成功。","type":"string","example":"200"},"Message":{"description":"返回信息描述，成功一般返回successful，错误时会返回相应错误信息。","type":"string","example":"successful"},"RequestId":{"description":"请求ID。","type":"string","example":"048A2164-3732-5DF5-88B5-F97FA56DAEB1"},"TaskId":{"description":"异步任务ID。可以调用DescribeTask获取任务结果。","type":"string","example":"t-0009qs5qcnvuvqrl2mxl"},"Success":{"description":"请求是否成功。\n\n- true：成功\n- false：失败","type":"boolean","example":"true"}}}}},"responseDemo":"[{\"type\":\"json\",\"example\":\"{\\n  \\\"Code\\\": \\\"200\\\",\\n  \\\"Message\\\": \\\"successful\\\",\\n  \\\"RequestId\\\": \\\"048A2164-3732-5DF5-88B5-F97FA56DAEB1\\\",\\n  \\\"TaskId\\\": \\\"t-0009qs5qcnvuvqrl2mxl\\\",\\n  \\\"Success\\\": true\\n}\",\"errorExample\":\"\"},{\"type\":\"xml\",\"example\":\"<UninstallClientResponse>\\n    <Code>200</Code>\\n    <Message>successful</Message>\\n    <RequestId>048A2164-3732-5DF5-88B5-F97FA56DAEB1</RequestId>\\n    <TaskId>t-0009qs5qcnvuvqrl2mxl</TaskId>\\n    <Success>true</Success>\\n</UninstallClientResponse>\",\"errorExample\":\"\"}]","title":"卸载客户端","summary":"调用UninstallClient接口卸载HBR备份客户端。","description":"调用该接口会卸载指定的HBR备份客户端，若要重新安装，请调用CreateClients接口。"}