{"methods":["post","get"],"schemes":["http","https"],"security":[{"AK":[]}],"operationType":"readAndWrite","deprecated":false,"systemTags":{"operationType":"delete"},"parameters":[{"name":"ClusterId","in":"query","schema":{"description":"实例ID。","type":"string","required":true,"docRequired":true,"example":"hb-bp16o0pd52e3y****"}},{"name":"NameService","in":"query","schema":{"description":"addUserHdfsInfo里的dfs.nameservices的值，会通过[QueryXpackRelateDB](~~144509~~)接口（relateDB为hdfs）时返回。","type":"string","required":true,"docRequired":true,"example":"hdfs_test"}}],"responses":{"200":{"schema":{"type":"object","properties":{"RequestId":{"description":"请求ID。","type":"string","example":"50373857-C47B-4B64-9332-D0B5280B59EA"}}}}},"errorCodes":{},"responseDemo":"[{\"type\":\"json\",\"example\":\"{\\n  \\\"RequestId\\\": \\\"50373857-C47B-4B64-9332-D0B5280B59EA\\\"\\n}\",\"errorExample\":\"\"},{\"type\":\"xml\",\"example\":\"<RequestId>50373857-C47B-4B64-9332-D0B5280B59EA</RequestId>\",\"errorExample\":\"\"}]","title":"删除Xpack里用户自建的hdfs信息","summary":"调用DeleteUserHdfsInfo删除Xpack里用户自建的hdfs信息。","requestParamsDescription":" ","responseParamsDescription":" ","extraInfo":" "}