{"path":"/openapi/instances/{InstanceId}/plugins/user/actions/install","methods":["post"],"schemes":["http","https"],"security":[{"AK":[]}],"operationType":"write","deprecated":false,"systemTags":{"operationType":"none"},"parameters":[{"name":"InstanceId","in":"path","schema":{"description":"实例ID。","type":"string","required":true,"docRequired":true,"example":"es-cn-i7m27ausp001l****"}},{"name":"body","in":"body","schema":{"type":"string","required":false,"docRequired":false}}],"responses":{"200":{"schema":{"type":"object","properties":{"RequestId":{"description":"请求ID。","type":"string","example":"5FFD9ED4-C2EC-4E89-B22B-1ACB6F*****"},"Result":{"type":"array","items":{"description":"请求安装的插件列表。如果安装失败，系统会返回对应的错误码，请参考错误码进行问题定位。","type":"string","example":"[\"pluginName1.zip\", \"pluginName2.zip\"]"}}}}}},"errorCodes":{"400":[{"errorCode":"InstanceActivating","errorMessage":"Instance is activating."},{"errorCode":"InstanceNotFound","errorMessage":"The instanceId provided does not exist."}]},"responseDemo":"[{\"type\":\"json\",\"example\":\"{\\n  \\\"RequestId\\\": \\\"5FFD9ED4-C2EC-4E89-B22B-1ACB6F*****\\\",\\n  \\\"Result\\\": [\\n    \\\"[\\\\\\\"pluginName1.zip\\\\\\\", \\\\\\\"pluginName2.zip\\\\\\\"]\\\"\\n  ]\\n}\",\"errorExample\":\"\"},{\"type\":\"xml\",\"example\":\"\",\"errorExample\":\"\"}]","title":"安装自定义插件","summary":"调用InstallUserPlugins，安装用户自定义的已经上传至Elasticsearch控制台的插件。","requestParamsDescription":"## RequestBody\nRequestBody中还需填入以下参数，用来指定自定义插件列表。\n| 参数 | 类型 | 是否必须 | 示例值 | 描述 |\n| --- | --- | --- | --- | --- |\n| RequestBody | Array |  |  |  |\n| └ name | String | 是 | pluginName1.zip | 用户自定义的已经上传至Elasticsearch控制台的插件。 |\n\n└表示子参数。\n\n示例如下：\n\n```\n[\n    {\"name\": \"pluginName1.zip\"},\n    {\"name\": \"pluginName2.zip\"}\n]\n\n```\n","responseParamsDescription":" ","extraInfo":" "}