{
  "name": "CreateUploadImage",
  "protocol": "HTTPS|HTTP",
  "method": "POST|GET",
  "path": "/",
  "timeout": 4000,
  "reqFormat": {
    "RegionId": {
      "name": "RegionId",
      "type": "String",
      "position": "System",
      "checkBlank": "false",
      "required": false,
      "docRequired": false
    },
    "ImageType": {
      "name": "ImageType",
      "type": "String",
      "position": "Query",
      "checkBlank": "false",
      "visibility": "Public",
      "required": true,
      "docRequired": true
    },
    "OwnerId": {
      "name": "OwnerId",
      "type": "Long",
      "position": "Query",
      "checkBlank": "false",
      "visibility": "Public",
      "required": false,
      "docRequired": false
    },
    "Title": {
      "name": "Title",
      "type": "String",
      "position": "Query",
      "checkBlank": "false",
      "visibility": "Public",
      "required": false,
      "docRequired": false
    },
    "ImageExt": {
      "name": "ImageExt",
      "type": "String",
      "position": "Query",
      "checkBlank": "false",
      "visibility": "Public",
      "required": false,
      "docRequired": false
    },
    "OriginalFileName": {
      "name": "OriginalFileName",
      "type": "String",
      "position": "Query",
      "checkBlank": "false",
      "visibility": "Public",
      "required": false,
      "docRequired": false
    },
    "Tags": {
      "name": "Tags",
      "type": "String",
      "position": "Query",
      "checkBlank": "false",
      "visibility": "Public",
      "required": false,
      "docRequired": false
    },
    "StorageLocation": {
      "name": "StorageLocation",
      "type": "String",
      "position": "Query",
      "checkBlank": "false",
      "visibility": "Public",
      "required": false,
      "docRequired": false
    },
    "CateId": {
      "name": "CateId",
      "type": "Long",
      "position": "Query",
      "checkBlank": "false",
      "visibility": "Public",
      "required": false,
      "docRequired": false
    },
    "UserData": {
      "name": "UserData",
      "type": "String",
      "position": "Query",
      "checkBlank": "false",
      "visibility": "Public",
      "required": false,
      "docRequired": false
    },
    "Description": {
      "name": "Description",
      "type": "String",
      "position": "Query",
      "checkBlank": "false",
      "visibility": "Public",
      "required": false,
      "docRequired": false
    },
    "AppId": {
      "name": "AppId",
      "type": "String",
      "position": "Query",
      "checkBlank": "false",
      "visibility": "Public",
      "required": false,
      "docRequired": false
    }
  },
  "res": {}
}