{"methods":["post","get"],"schemes":["http","https"],"security":[{"AK":[]},{"BearerToken":[]}],"operationType":"write","deprecated":false,"systemTags":{},"parameters":[{"name":"InstanceId","in":"query","schema":{"description":"实例ID。","type":"string","required":true,"docRequired":true,"example":"ccc-test"}},{"name":"RamIdList","in":"query","schema":{"description":"阿里云RAM账户的UID列表，格式为JSON数组的字符串，数组元素最多20个。","type":"string","required":true,"docRequired":true,"example":"[\"26972543893791****\"]"}}],"responses":{"200":{"schema":{"description":"响应数据","type":"object","properties":{"HttpStatusCode":{"description":"HTTP状态码。","type":"integer","format":"int32","example":"200"},"RequestId":{"description":"请求ID。","type":"string","example":"1CDB5C94-ACFB-59B5-85FE-C1DAF8049C63"},"Code":{"description":"响应码。","type":"string","example":"OK"},"Message":{"description":"响应信息。","type":"string","example":"无"},"Data":{"description":"数据。","type":"array","items":{"type":"object","properties":{"InstanceId":{"description":"实例ID。","type":"string","example":"ccc-test"},"UserId":{"description":"坐席ID。","type":"string","example":"agent@ccc-test"},"RoleId":{"description":"角色ID。","type":"string","example":"Admin@ccc-test"},"Extension":{"description":"坐席分机号。","type":"string","example":"8021****"},"RamId":{"description":"阿里云RAM账户的UID。","type":"string","example":"26972543893791****"}}}}}}}},"errorCodes":{"400":[{"errorCode":"Parameter.Enumeration","errorMessage":"The parameter %s must be one of the value of enumeration %s."},{"errorCode":"Parameter.Maximum","errorMessage":"The parameter %s must be less than or equal to %s."},{"errorCode":"Parameter.Minimum","errorMessage":"The parameter %s must be greater than or equal to %s."},{"errorCode":"Parameter.Blank","errorMessage":"The parameter %s may not be null or blank."},{"errorCode":"Parameter.Empty","errorMessage":"The parameter %s may not be null or empty."}],"404":[{"errorCode":"NotExists.InstanceId","errorMessage":"The specified instance %s does not exist."}]},"responseDemo":"[{\"errorExample\":\"\",\"example\":\"{\\n  \\\"HttpStatusCode\\\": 200,\\n  \\\"RequestId\\\": \\\"1CDB5C94-ACFB-59B5-85FE-C1DAF8049C63\\\",\\n  \\\"Code\\\": \\\"OK\\\",\\n  \\\"Message\\\": \\\"无\\\",\\n  \\\"Data\\\": [\\n    {\\n      \\\"InstanceId\\\": \\\"ccc-test\\\",\\n      \\\"UserId\\\": \\\"agent@ccc-test\\\",\\n      \\\"RoleId\\\": \\\"Admin@ccc-test\\\",\\n      \\\"Extension\\\": \\\"8021****\\\",\\n      \\\"RamId\\\": \\\"26972543893791****\\\"\\n    }\\n  ]\\n}\",\"type\":\"json\"}]","title":"导入多个管理员","summary":"调用ImportAdmins导入一个或多个管理员到指定实例下，调用者需要拥有AliyunCCCFullAccess的权限，可以在RAM控制台进行授权。"}