{"methods":["get","post"],"schemes":["https"],"security":[{"AK":[]}],"operationType":"read","deprecated":false,"systemTags":{"operationType":"get","riskType":"none","chargeType":"free"},"parameters":[{"name":"KmsInstanceId","in":"query","schema":{"title":"A short description of struct","description":"要查询的KMS实例的ID。","type":"string","required":true,"example":"kst-bjj62f5ba3dnpb6v8****"}}],"responses":{"200":{"schema":{"title":"Schema of Response","description":"KMS实例详情。","type":"object","properties":{"RequestId":{"title":"Id of the request","description":"本次调用请求的ID，是由阿里云为该请求生成的唯一标识符，可用于排查和定位问题。","type":"string","example":"46b4a94a-57d2-44b4-9810-1e87d31abb33"},"KmsInstance":{"description":"KMS实例详情。","type":"object","properties":{"InstanceId":{"description":"KMS实例的ID。","type":"string","example":"kst-bjj62f5ba3dnpb6v8****"},"InstanceName":{"description":"KMS实例的名称。","type":"string","example":"kst-bjj62f5ba3dnpb6v8****"},"Status":{"description":"KMS实例的状态。取值：\n\n- Uninitialized：未启用\n- Connecting：连接中\n- Connected：已启用\n- Disconnected：已断开\n- Error：状态异常\n\n","type":"string","example":"Connected"},"CreateTime":{"description":"KMS实例创建的时间。","type":"string","example":"2023-09-05T12:44:20Z"},"Spec":{"description":"KMS实例的计算性能。","type":"integer","format":"int64","example":"1000"},"KeyNum":{"description":"KMS实例支持创建的密钥数量。","type":"integer","format":"int64","example":"1000"},"SecretNum":{"description":"KMS实例支持创建的凭据数量。","type":"string","example":"10"},"VpcNum":{"description":"KMS实例的访问管理总量。","type":"integer","format":"int64","example":"5"},"VpcId":{"description":"KMS实例绑定的VPC。","type":"string","example":"vpc-bp19z7cwmltad5dff****"},"ZoneIds":{"description":"KMS实例绑定的可用区。","type":"string","example":"\"cn-hangzhou-k\",       \"cn-hangzhou-j\""},"VswitchIds":{"description":"KMS实例绑定的VPC中的交换机。","type":"string","example":"vsw-bp1i512amda6d10a0****"},"EndDate":{"title":"到期时间\n","description":"KMS实例的到期时间。","type":"string","example":"2023-10-05T16:00:00Z"},"StartDate":{"description":"KMS实例启用的时间。","type":"string","example":"2023-09-05T12:44:19Z"},"CaCertificateChainPem":{"description":"KMS实例的CA证书的内容。","type":"string","example":"-----BEGIN CERTIFICATE-----\\r\\nMIIDuzCCAqOgAwIBAgIJALTKwWAjvbMiMA0GCSqGSIb3DQEBCwUAMHQxCzAJBgNV****-----END CERTIFICATE-----"},"BindVpcs":{"type":"object","properties":{"BindVpc":{"description":"配置的VPC列表。\n>如果您的自建应用部署在同地域的多个VPC中，除了KMS实例所属的VPC（即启用KMS实例时设置的VPC）外，您还可以将其他VPC配置到KMS实例中，这些VPC可以属于同一个阿里云账号，也可以属于不同阿里云账号。配置完成后，在这些VPC中的自建应用即可以访问指定的KMS实例。","type":"array","items":{"description":"配置的VPC列表。\n>如果您的自建应用部署在同地域的多个VPC中，除了KMS实例绑定的VPC，您还可以将其他VPC配置到KMS实例中，这些VPC可以属于同一个阿里云账号，也可以属于不同阿里云账号。配置完成后，在这些VPC中的自建应用即可以访问指定的KMS实例。","type":"object","properties":{"RegionId":{"description":"VPC所属的地域。","type":"string","example":"cn-hangzhou"},"VpcId":{"description":"VPC的ID。","type":"string","example":"vpc-bp19z7djuhtad5dff****"},"VpcOwnerId":{"description":"VPC所属的阿里云账号。","type":"string","example":"190325303126****"},"VSwitchId":{"description":"VPC下的交换机。","type":"string","example":"vsw-bp1i512amhdje10f1****"}}}}}}}}}}}},"errorCodes":{"400":[{"errorCode":"IllegalTimestamp","errorMessage":"The input parameter Timestamp that is mandatory for processing this request is not supplied."}]},"staticInfo":{"returnType":"synchronous"},"responseDemo":"[{\"type\":\"json\",\"example\":\"{\\n  \\\"RequestId\\\": \\\"46b4a94a-57d2-44b4-9810-1e87d31abb33\\\",\\n  \\\"KmsInstance\\\": {\\n    \\\"InstanceId\\\": \\\"kst-bjj62f5ba3dnpb6v8****\\\",\\n    \\\"InstanceName\\\": \\\"kst-bjj62f5ba3dnpb6v8****\\\",\\n    \\\"Status\\\": \\\"Connected\\\",\\n    \\\"CreateTime\\\": \\\"2023-09-05T12:44:20Z\\\",\\n    \\\"Spec\\\": 1000,\\n    \\\"KeyNum\\\": 1000,\\n    \\\"SecretNum\\\": \\\"10\\\",\\n    \\\"VpcNum\\\": 5,\\n    \\\"VpcId\\\": \\\"vpc-bp19z7cwmltad5dff****\\\",\\n    \\\"ZoneIds\\\": \\\"\\\\\\\"cn-hangzhou-k\\\\\\\",       \\\\\\\"cn-hangzhou-j\\\\\\\"\\\",\\n    \\\"VswitchIds\\\": \\\"vsw-bp1i512amda6d10a0****\\\",\\n    \\\"EndDate\\\": \\\"2023-10-05T16:00:00Z\\\",\\n    \\\"StartDate\\\": \\\"2023-09-05T12:44:19Z\\\",\\n    \\\"CaCertificateChainPem\\\": \\\"-----BEGIN CERTIFICATE-----\\\\\\\\r\\\\\\\\nMIIDuzCCAqOgAwIBAgIJALTKwWAjvbMiMA0GCSqGSIb3DQEBCwUAMHQxCzAJBgNV****-----END CERTIFICATE-----\\\",\\n    \\\"BindVpcs\\\": {\\n      \\\"BindVpc\\\": [\\n        {\\n          \\\"RegionId\\\": \\\"cn-hangzhou\\\",\\n          \\\"VpcId\\\": \\\"vpc-bp19z7djuhtad5dff****\\\",\\n          \\\"VpcOwnerId\\\": \\\"190325303126****\\\",\\n          \\\"VSwitchId\\\": \\\"vsw-bp1i512amhdje10f1****\\\"\\n        }\\n      ]\\n    }\\n  }\\n}\",\"errorExample\":\"\"},{\"type\":\"xml\",\"example\":\"<GetKmsInstanceResponse>\\n    <RequestId>46b4a94a-57d2-44b4-9810-1e87d31abb33</RequestId>\\n    <KmsInstance>\\n        <InstanceId>kst-bjj62f5ba3dnpb6v8****</InstanceId>\\n        <InstanceName>kst-bjj62f5ba3dnpb6v8****</InstanceName>\\n        <Status>Connected</Status>\\n        <CreateTime>2023-09-05T12:44:20Z</CreateTime>\\n        <Spec>1000</Spec>\\n        <KeyNum>1000</KeyNum>\\n        <SecretNum>10</SecretNum>\\n        <VpcNum>5</VpcNum>\\n        <VpcId>vpc-bp19z7cwmltad5dff****</VpcId>\\n        <ZoneIds>\\\"cn-hangzhou-k\\\",       \\\"cn-hangzhou-j\\\"</ZoneIds>\\n        <VswitchIds>vsw-bp1i512amda6d10a0****</VswitchIds>\\n        <EndDate>2023-10-05T16:00:00Z</EndDate>\\n        <StartDate>2023-09-05T12:44:19Z</StartDate>\\n        <CaCertificateChainPem>-----BEGIN CERTIFICATE-----\\\\r\\\\nMIIDuzCCAqOgAwIBAgIJALTKwWAjvbMiMA0GCSqGSIb3DQEBCwUAMHQxCzAJBgNV****-----END CERTIFICATE-----</CaCertificateChainPem>\\n        <BindVpcs>\\n            <RegionId>cn-hangzhou</RegionId>\\n            <VpcId>vpc-bp19z7djuhtad5dff****</VpcId>\\n            <VpcOwnerId>190325303126****</VpcOwnerId>\\n            <VSwitchId>vsw-bp1i512amhdje10f1****</VSwitchId>\\n        </BindVpcs>\\n    </KmsInstance>\\n</GetKmsInstanceResponse>\",\"errorExample\":\"\"}]","title":"获取实例","summary":"查询一个KMS实例的详情。"}