{"methods":["post","get"],"schemes":["http","https"],"security":[{"AK":[]}],"operationType":"readAndWrite","deprecated":false,"systemTags":{"operationType":"none","abilityTreeCode":"132459","abilityTreeNodes":["FEATUREdrds7CT80F"]},"parameters":[{"name":"RegionId","in":"query","schema":{"type":"string","required":true,"docRequired":true}},{"name":"DBInstanceName","in":"query","schema":{"type":"string","required":true,"docRequired":true}},{"name":"StorageInstanceName","in":"query","schema":{"type":"string"}},{"name":"SwitchTime","in":"query","schema":{"type":"string"}},{"name":"SwitchTimeMode","in":"query","schema":{"type":"string"}}],"responses":{"200":{"schema":{"type":"object","properties":{"Message":{"type":"string"},"RequestId":{"type":"string"},"Success":{"type":"boolean"}}}}}}