{"methods":["post","get"],"schemes":["http","https"],"security":[{"AK":[]}],"operationType":"write","deprecated":false,"systemTags":{},"parameters":[{"name":"RegionId","in":"query","schema":{"description":"地域ID。","type":"string","required":true,"docRequired":true,"example":"cn-hangzhou"}},{"name":"DBInstanceName","in":"query","schema":{"description":"实例ID。","type":"string","required":true,"docRequired":true,"example":"pxc-hzjasd****"}},{"name":"TargetDBInstanceClass","in":"query","schema":{"description":"变配目标规格：\n\n- **polarx.x4.medium.2e**：2核8G\n- **polarx.x4.large.2e**：4核16G\n- **polarx.x8.large.2e**：4核32G\n- **polarx.x4.xlarge.2e**：8核32G\n- **polarx.x8.xlarge.2e**：8核64G\n- **polarx.x4.2xlarge.2e**：16核64G\n- **polarx.x8.2xlarge.2e**：16核128G\n- **polarx.x4.4xlarge.2e**：32核128G\n- **polarx.x8.4xlarge.2e**：32核256G\n- **polarx.st.8xlarge.2e**：60核470G\n- **polarx.st.12xlarge.2e**：90核720G","type":"string","required":false,"docRequired":true,"example":"polarx.x4.xlarge.2e"}},{"name":"ClientToken","in":"query","schema":{"description":"客户端token，保证唯一任意字符串。","type":"string","required":false,"docRequired":true,"example":"FEA5DC20-6D8A-5979-97AA-FC57546ADC20"}},{"name":"CnClass","in":"query","schema":{"description":"计算节点规格。","type":"string","required":false,"example":"4核32G"}},{"name":"DnClass","in":"query","schema":{"description":"存储节点规格。","type":"string","required":false,"example":"4核32G"}},{"name":"SpecifiedDNScale","in":"query","allowEmptyValue":true,"schema":{"type":"boolean","required":false,"default":"false"}},{"name":"SpecifiedDNSpecMapJson","in":"query","allowEmptyValue":true,"schema":{"type":"string","required":false}},{"name":"SwitchTimeMode","in":"query","schema":{"type":"string","required":false}},{"name":"SwitchTime","in":"query","schema":{"type":"string","required":false}}],"responses":{"200":{"schema":{"type":"object","properties":{"OrderId":{"description":"交易订单ID，实例升配或降配，变更实例规格，会产生交易订单。","type":"string","example":"20211103105558"},"RequestId":{"description":"请求ID。","type":"string","example":"FEA5DC20-6D8A-5979-97AA-FC57546ADC20"}}}}},"responseDemo":"[{\"type\":\"json\",\"example\":\"{\\n  \\\"OrderId\\\": \\\"20211103105558\\\",\\n  \\\"RequestId\\\": \\\"FEA5DC20-6D8A-5979-97AA-FC57546ADC20\\\"\\n}\",\"errorExample\":\"\"},{\"type\":\"xml\",\"example\":\"<ModifyDBInstanceClassResponse>\\n    <OrderId>20211103105558</OrderId>\\n    <RequestId>FEA5DC20-6D8A-5979-97AA-FC57546ADC20</RequestId>\\n</ModifyDBInstanceClassResponse>\",\"errorExample\":\"\"}]","title":"修改实例规格","summary":"调用ModifyDBInstanceClass接口修改实例规格。"}