{"summary":"调用UpdateTemplate接口修改云剪辑模板，支持修改模板标题、模板配置等信息。","methods":["get","post"],"schemes":["http","https"],"security":[{"AK":[]}],"operationType":"write","deprecated":false,"systemTags":{},"parameters":[{"name":"TemplateId","in":"query","schema":{"title":"模板ID","description":"云剪辑模板ID。可通过[智能媒体服务控制台](https://ice.console.aliyun.com/production/template/list/common)或[创建模板](~~441161~~)的返回参数中获取。","type":"string","required":false,"example":"23923ec3318f4c359e42e1e5b296****"}},{"name":"Name","in":"query","schema":{"title":"模板名称","description":"云剪辑模板名称。","type":"string","required":false,"example":"云剪辑模板1"}},{"name":"Config","in":"formData","schema":{"title":"参见模板Config文档","description":"模板配置。详细说明请参见[普通模板Config详解](~~456193~~)。","type":"string","required":false,"example":"{\n    \"VideoTracks\": [\n        {\n            \"VideoTrackClips\": [\n                {\n                    \"Sys_Type\" : \"ArrayItems\",\n                    \"Sys_ArrayObject\" : \"$VideoArray\",\n                    \"Sys_Template\" : {\n                        \"MediaId\" : \"$MediaId\"\n                    }\n                }\n            ]\n        }\n    ]\n}"}},{"name":"CoverUrl","in":"query","schema":{"title":"模板封面","description":"模板封面地址。","type":"string","required":false,"example":"http://example-bucket.oss-cn-shanghai.aliyuncs.com/cover.jpg"}},{"name":"PreviewMedia","in":"query","schema":{"title":"预览视频媒资id","description":"预览视频媒资ID。","type":"string","required":false,"example":"1ae320b48fb04483915d4f2cd8ac****"}},{"name":"Status","in":"query","schema":{"title":"模板状态","description":"模板状态，取值范围：\n- Available：正常。\n- Created：已创建，还不能使用。\n- Uploading：上传中。\n- Processing：高级模板分析中。\n- UploadFailed：上传失败。\n- ProcessFailed：高级模板分析失败。\n\n> 高级模板创建后有解析时间，状态为Processing，此时模板不可用，当模板状态为Available方可使用。模板解析时间与模板文件大小有关，一般10s-5min。","type":"string","required":false,"example":"Available"}},{"name":"Source","in":"query","schema":{"title":"修改来源，默认OpenAPI","description":"修改来源，默认OpenAPI，取值范围：\n- AliyunConsole：通过阿里云控制台创建。\n- OpenAPI：通过OpenAPI创建。\n- WebSDK：通过WebSDK创建。","type":"string","required":false,"example":"OpenAPI"}},{"name":"RelatedMediaids","in":"query","schema":{"title":"模板相关素材，模板编辑器使用","description":"模板关联素材，普通模板编辑器使用。","type":"string","required":false,"example":"{\"video\":[\"f64c6acc840247edb6b12f575c66****\",\"9675dcf040ba4525bb037c29d156****\"],\"audio\":[\"62a54019d9114009a5ae9bcfd70b****\"],\"image\":[\"743ffbeb7e004c758cdc1fb34c04****\"]}"}}],"responses":{"200":{"schema":{"title":"Schema of Response","description":"返回参数。","type":"object","properties":{"RequestId":{"title":"请求ID","description":"请求ID。","type":"string","example":"F8D475A5-F2EC-5755-ABD8-22D5561C****"}}}}},"responseDemo":"[{\"type\":\"json\",\"example\":\"{\\n  \\\"RequestId\\\": \\\"F8D475A5-F2EC-5755-ABD8-22D5561C****\\\"\\n}\",\"errorExample\":\"\"},{\"type\":\"xml\",\"example\":\"<UpdateTemplateResponse>\\n    <RequestId>******11-DB8D-4A9A-875B-275798******</RequestId>\\n</UpdateTemplateResponse>\",\"errorExample\":\"\"}]","title":"修改模板","description":"- 使用普通模板，请参考：[普通模板快速入门](https://help.aliyun.com/document_detail/270942.html)。\n- 使用高级模板，请参考：[高级模板创建及使用](https://help.aliyun.com/document_detail/291418.html)。"}