{"summary":"查询网络型负载均衡监听列表。","methods":["get","post"],"schemes":["http","https"],"security":[{"AK":[]}],"operationType":"read","deprecated":false,"systemTags":{"operationType":"get"},"parameters":[{"name":"ListenerIds","in":"query","style":"repeatList","schema":{"title":"监听唯一标识","description":"监听实例ID。最多支持20个监听ID。","type":"array","items":{"description":"监听实例ID。最多支持20个监听ID。","type":"string","required":false,"example":"lsn-bp1bpn0kn908w4nbw****"},"required":false,"maxItems":20}},{"name":"LoadBalancerIds","in":"query","style":"repeatList","schema":{"title":"负载均衡实例标识","description":"网络型负载均衡实例ID。最多支持20个实例ID。","type":"array","items":{"description":"网络型负载均衡实例ID。最多支持20个实例ID。","type":"string","required":false,"example":"nlb-83ckzc8d4xlp8o****"},"required":false,"maxItems":20}},{"name":"ListenerProtocol","in":"query","schema":{"title":"监听协议","description":"监听协议。取值：**TCP**、**UDP**或**TCPSSL**。","type":"string","required":false,"example":"TCPSSL"}},{"name":"Tag","in":"query","style":"flat","schema":{"description":"标签列表。","type":"array","items":{"description":"标签。","type":"object","properties":{"Key":{"description":"实例的标签键。最多支持输入20个标签键。一旦输入该值，则不允许为空字符串。\n\n最多支持64个字符，不能以`aliyun`和`acs:`开头，不能包含`http://`或者`https://`。","type":"string","required":false,"example":"env"},"Value":{"description":"实例的标签值。最多支持输入20个标签值。一旦输入该值，可以为空字符串。\n\n最多支持128个字符，不能以`aliyun`和`acs:`开头，不能包含`http://`或者`https://`。","type":"string","required":false,"example":"product"}},"required":false},"required":false,"maxItems":20,"minItems":1}},{"name":"NextToken","in":"query","schema":{"description":"是否拥有下一次查询的令牌（Token）。取值：\n- 第一次查询和没有下一次查询时，均无需填写。\n- 如果有下一次查询，取值为上一次API调用返回的NextToken值。","type":"string","required":false,"example":"FFmyTO70tTpLG6I3FmYAXGKPd****"}},{"name":"MaxResults","in":"query","schema":{"description":"分批次查询时每次显示的条目数。取值范围：**1**~**100**，默认值为**20**。","type":"integer","format":"int32","required":false,"example":"20"}},{"name":"RegionId","in":"query","schema":{"description":"网络型负载均衡实例所在的地域ID。 \n\n您可以通过调用[DescribeRegions](~~443657~~)接口获取地域ID。","type":"string","required":false,"example":"cn-hangzhou"}}],"responses":{"200":{"schema":{"title":"RpcResponse<ListListenersResponse>","description":"查询监听列表。","type":"object","properties":{"RequestId":{"description":"请求ID。","type":"string","example":"CEF72CEB-54B6-4AE8-B225-F876FF7BA984"},"Listeners":{"description":"网络型负载均衡监听列表。","type":"array","items":{"description":"网络型负载均衡监听列表。","type":"object","properties":{"Tags":{"description":"标签列表。","type":"array","items":{"description":"标签。","type":"object","properties":{"Key":{"description":"标签键。","type":"string","example":"Created"},"Value":{"description":"标签值。","type":"string","example":"TF"}}}},"LoadBalancerId":{"description":"网络型负载均衡实例ID。","type":"string","example":"nlb-83ckzc8d4xlp8o****"},"ListenerId":{"title":"自己生成后赋值","description":"监听ID。","type":"string","example":"lsn-ga6sjjcll6ou34l1et****"},"ListenerProtocol":{"title":"监听协议 (TCP, UDP, TCPSSL, GENEVE)","description":"监听协议。取值：**TCP**、**UDP**或**TCPSSL**。","type":"string","example":"TCPSSL"},"ListenerPort":{"title":"监听端口","description":"监听端口。","type":"integer","format":"int32","example":"443"},"StartPort":{"title":"anyPort监听起始端口","description":"全端口监听起始端口。","type":"string","example":"233"},"EndPort":{"title":"anyPort监听结束端口","description":"全端口监听结束端口。","type":"string","example":"455"},"ListenerDescription":{"title":"监听描述","description":"自定义监听名称。\n\n长度限制为2~256个字符，支持中文和英文字母，可包含数字、半角逗号（,）、半角句号（.）、半角分号（;）、正斜线（/）、at（@）、下划线（_）和短划线（-）。","type":"string","example":"tcpssl_443"},"ServerGroupId":{"title":"servergroupId","description":"服务器组ID。","type":"string","example":"sgp-ppdpc14gdm3x4o****"},"IdleTimeout":{"title":"空闲超时时间","description":"连接空闲超时时间。单位：秒。取值范围：**1**~**900**。默认值：**900**。","type":"integer","format":"int32","example":"900"},"SecurityPolicyId":{"title":"Tclssl监听的安全策略","description":"安全策略ID。\n\n> 仅对TCPSSL监听生效。","type":"string","example":"tls_cipher_policy_1_1"},"CertificateIds":{"title":"server证书列表","description":"服务器证书列表信息。\n\n> 仅对TCPSSL监听生效。","type":"array","items":{"description":"服务器证书列表信息。\n\n> 仅对TCPSSL监听生效。","type":"string","example":"123157******"}},"CaCertificateIds":{"title":"ca 证书列表","description":"CA证书列表信息。\n> 仅对TCPSSL监听生效。","type":"array","items":{"description":"CA证书列表信息。\n> 仅对TCPSSL监听生效。","type":"string","example":"139a00******"}},"CaEnabled":{"description":"是否启动双向认证。取值：\n\n- **true**：启动。\n\n- **false**：关闭。","type":"boolean","example":"false"},"ListenerStatus":{"description":"当前监听的状态，取值：\n\n- **Provisioning**：创建中。\n\n- **Running**：运行中。\n\n- **Configuring**：配置中。\n\n- **Stopping**：停止中。\n\n- **Stopped**：已停止。\n\n- **Starting**：启动中。\n\n- **Deleting**：删除中。\n\n- **Deleted**：已删除。","type":"string","example":"Running"},"RegionId":{"title":"业务location","description":"网络型负载均衡实例所在的地域ID。 ","type":"string","example":"cn-hangzhou"},"AlpnEnabled":{"description":"是否开启ALPN。取值：\n\n- **true**：开启。\n\n- **false**：关闭。","type":"boolean","example":"false"},"AlpnPolicy":{"description":"ALPN策略。取值：\n\n- **HTTP1Only**\n- **HTTP2Only**\n- **HTTP2Preferred**\n- **HTTP2Optional**","type":"string","example":"HTTP1Only"},"SecSensorEnabled":{"description":"是否开启秒级监控功能。取值：\n\n- **true**：开启。\n\n- **false**：关闭。","type":"boolean","example":"false"},"ProxyProtocolEnabled":{"description":"是否开启通过Proxy Protocol协议携带客户端源地址到后端服务器。取值：\n\n- **true**：开启。\n\n- **false**：关闭。","type":"boolean","example":"false"},"ProxyProtocolV2Config":{"description":"通过Proxy Protocol协议携带VpcId、PrivateLinkEpId、PrivateLinkEpsId信息到后端服务器配置。","type":"object","properties":{"Ppv2VpcIdEnabled":{"description":"是否开启通过Proxy Protocol协议携带VpcId到后端服务器。取值：\n\n- **true**：开启。\n\n- **false**：关闭。","type":"boolean","example":"false"},"Ppv2PrivateLinkEpIdEnabled":{"description":"是否开启通过Proxy Protocol协议携带PrivateLinkEpId到后端服务器。取值：\n\n- **true**：开启。\n\n- **false**：关闭。","type":"boolean","example":"false"},"Ppv2PrivateLinkEpsIdEnabled":{"description":"是否开启通过Proxy Protocol协议携带PrivateLinkEpsId到后端服务器。取值：\n\n- **true**：开启。\n\n- **false**：关闭。","type":"boolean","example":"false"}}},"Cps":{"description":"网络型负载均衡实例每秒新建连接限速值。取值范围：**0**~**1000000**。**0**表示不限速。","type":"integer","format":"int32","example":"1000"},"Mss":{"description":"TCP报文的最大段大小。单位：字节，取值范围：**0**~**1500**。**0**表示不修改用户TCP报文的MSS值。\n\n> 仅TCP、TCPSSL类型的监听支持该字段值。","type":"integer","format":"int32","example":"200"}}}},"TotalCount":{"description":"列表条目数。","type":"integer","format":"int32","example":"4"},"NextToken":{"description":"是否拥有下一次查询的令牌（Token）。取值：\n- 如果**NextToken**为空表示没有下一次查询。\n- 如果**NextToken**有返回值，该取值表示下一次查询开始的令牌。","type":"string","example":"FFmyTO70tTpLG6I3FmYAXGKPd****"},"MaxResults":{"description":"分批次查询时每次显示的条目数。","type":"integer","format":"int32","example":"20"}}}}},"errorCodes":{"400":[{"errorCode":"SystemBusy","errorMessage":"System is busy, please try again later."},{"errorCode":"IllegalParam","errorMessage":"The param of %s is illegal."}],"403":[{"errorCode":"Forbidden.NoPermission","errorMessage":"Authentication is failed for NoPermission."}]},"responseDemo":"[{\"type\":\"json\",\"example\":\"{\\n  \\\"RequestId\\\": \\\"CEF72CEB-54B6-4AE8-B225-F876FF7BA984\\\",\\n  \\\"Listeners\\\": [\\n    {\\n      \\\"Tags\\\": [\\n        {\\n          \\\"Key\\\": \\\"Created\\\",\\n          \\\"Value\\\": \\\"TF\\\"\\n        }\\n      ],\\n      \\\"LoadBalancerId\\\": \\\"nlb-83ckzc8d4xlp8o****\\\",\\n      \\\"ListenerId\\\": \\\"lsn-ga6sjjcll6ou34l1et****\\\",\\n      \\\"ListenerProtocol\\\": \\\"TCPSSL\\\",\\n      \\\"ListenerPort\\\": 443,\\n      \\\"StartPort\\\": \\\"233\\\",\\n      \\\"EndPort\\\": \\\"455\\\",\\n      \\\"ListenerDescription\\\": \\\"tcpssl_443\\\",\\n      \\\"ServerGroupId\\\": \\\"sgp-ppdpc14gdm3x4o****\\\",\\n      \\\"IdleTimeout\\\": 900,\\n      \\\"SecurityPolicyId\\\": \\\"tls_cipher_policy_1_1\\\",\\n      \\\"CertificateIds\\\": [\\n        \\\"123157******\\\"\\n      ],\\n      \\\"CaCertificateIds\\\": [\\n        \\\"139a00******\\\"\\n      ],\\n      \\\"CaEnabled\\\": false,\\n      \\\"ListenerStatus\\\": \\\"Running\\\",\\n      \\\"RegionId\\\": \\\"cn-hangzhou\\\",\\n      \\\"AlpnEnabled\\\": false,\\n      \\\"AlpnPolicy\\\": \\\"HTTP1Only\\\",\\n      \\\"SecSensorEnabled\\\": false,\\n      \\\"ProxyProtocolEnabled\\\": false,\\n      \\\"ProxyProtocolV2Config\\\": {\\n        \\\"Ppv2VpcIdEnabled\\\": false,\\n        \\\"Ppv2PrivateLinkEpIdEnabled\\\": false,\\n        \\\"Ppv2PrivateLinkEpsIdEnabled\\\": false\\n      },\\n      \\\"Cps\\\": 1000,\\n      \\\"Mss\\\": 200\\n    }\\n  ],\\n  \\\"TotalCount\\\": 4,\\n  \\\"NextToken\\\": \\\"FFmyTO70tTpLG6I3FmYAXGKPd****\\\",\\n  \\\"MaxResults\\\": 20\\n}\",\"errorExample\":\"\"},{\"type\":\"xml\",\"example\":\"<ListListenersResponse>\\n    <RequestId>CEF72CEB-54B6-4AE8-B225-F876FF7BA984</RequestId>\\n    <Listeners>\\n        <LoadBalancerId>nlb-83ckzc8d4xlp8o****</LoadBalancerId>\\n        <ListenerId>lsn-ga6sjjcll6ou34l1et****</ListenerId>\\n        <ListenerProtocol>TCPSSL</ListenerProtocol>\\n        <ListenerPort>443</ListenerPort>\\n        <StartPort>233</StartPort>\\n        <EndPort>455</EndPort>\\n        <ListenerDescription>tcpssl_443</ListenerDescription>\\n        <ServerGroupId>sgp-ppdpc14gdm3x4o****</ServerGroupId>\\n        <IdleTimeout>900</IdleTimeout>\\n        <SecurityPolicyId>tls_cipher_policy_1_1</SecurityPolicyId>\\n        <CertificateIds>12315790212_166f8204689_1714763408_70998****</CertificateIds>\\n        <CaCertificateIds>139a00604ad-cn-east-hangzh****</CaCertificateIds>\\n        <CaEnabled>false</CaEnabled>\\n        <ListenerStatus>Running</ListenerStatus>\\n        <RegionId>cn-hangzhou</RegionId>\\n        <AlpnEnabled>false</AlpnEnabled>\\n        <AlpnPolicy>ALPN</AlpnPolicy>\\n        <SecSensorEnabled>false</SecSensorEnabled>\\n        <ProxyProtocolEnabled>false</ProxyProtocolEnabled>\\n        <Cps>1000</Cps>\\n        <Mss>200</Mss>\\n    </Listeners>\\n    <TotalCount>4</TotalCount>\\n    <NextToken>FFmyTO70tTpLG6I3FmYAXGKPd****</NextToken>\\n    <MaxResults>20</MaxResults>\\n</ListListenersResponse>\",\"errorExample\":\"\"}]","title":"查询监听"}