{"methods":["post"],"schemes":["http","https"],"security":[{"AK":[]}],"operationType":"read","deprecated":false,"systemTags":{"operationType":"get","abilityTreeCode":"78235","abilityTreeNodes":["FEATUREdide7T0EJX"]},"parameters":[{"name":"TenantId","in":"formData","schema":{"description":"租户ID。","type":"integer","format":"int64","required":false,"docRequired":false,"example":"10002"}},{"name":"ProjectId","in":"formData","schema":{"description":"工作空间的ID。","type":"integer","format":"int64","required":true,"docRequired":true,"example":"10001"}},{"name":"ApiId","in":"formData","schema":{"description":"数据服务API的ID。","type":"integer","format":"int64","required":true,"docRequired":true,"example":"10000"}}],"responses":{"200":{"schema":{"description":"返回对象","type":"object","properties":{"HttpStatusCode":{"description":"HTTP状态码。","type":"integer","format":"int32","example":"200"},"RequestId":{"description":"请求ID，一次请求的唯一标识。\n","type":"string","example":"0000-ABCD-EFG****"},"ErrorMessage":{"description":"错误信息。","type":"string","example":"The specified parameters are invalid."},"Success":{"description":"调用是否成功。\n","type":"boolean","example":"true"},"ErrorCode":{"description":"错误码。","type":"string","example":"1031203110005"},"Data":{"description":"返回数据。","type":"object","properties":{"Timeout":{"description":"超时时间，单位为毫秒（ms）。","type":"integer","format":"int32","example":"10000"},"Status":{"description":"API的状态，可选枚举值包括0（未发布）和1（已发布）。\n","type":"integer","format":"int32","example":"0"},"ApiId":{"description":"数据服务API的ID。","type":"integer","format":"int64","example":"10000"},"ApiMode":{"description":"API的类型，可选枚举值包括0（向导API）、1（脚本API）和2（注册API）。","type":"integer","format":"int32","example":"0"},"ProjectId":{"description":"工作空间的ID。","type":"integer","format":"int64","example":"10001"},"ResponseContentType":{"description":"API的返回数据类型，可选枚举值包括0（JSON）和1（XML）。向导和脚本API支持JSON，注册API支持JSON和XML。","type":"integer","format":"int32","example":"0"},"CreatorId":{"description":"创建人的阿里云ID。","type":"string","example":"1234567"},"VisibleRange":{"description":"可见范围，可选枚举值包括0（工作空间）和1（私有）。\n","type":"integer","format":"int32","example":"0"},"ModifiedTime":{"description":"最新修改时间。","type":"string","example":"2020-06-23T00:21:01+0800"},"OperatorId":{"description":"最新编辑人的阿里云ID。","type":"string","example":"2345678"},"GroupId":{"description":"分组ID。","type":"string","example":"ab123****"},"Description":{"description":"描述信息。","type":"string","example":"测试API描述"},"FolderId":{"description":"文件夹ID","type":"integer","format":"int64","example":"0"},"RequestMethod":{"description":"API的请求方式，可选枚举值包括0（GET）、1（POST）、2（PUT）和3（DELETE）。向导和脚本API支持GET和POST。注册API支持GET、POST、PUT和DELETE。","type":"integer","format":"int32","example":"0"},"CreatedTime":{"description":"创建时间。","type":"string","example":"2020-06-23T00:21:01+0800"},"ApiName":{"description":"API的名称。","type":"string","example":"测试API名称"},"TenantId":{"description":"租户ID。","type":"integer","format":"int64","example":"10002"},"ApiPath":{"description":"API的路径。","type":"string","example":"/test/1"},"Protocols":{"description":"字段列表","type":"array","items":{"description":"API协议，多值列表，可选枚举值包括0（HTTP）和1（HTTPS）。","type":"integer","format":"int32","example":"0"}},"RegistrationDetails":{"description":"注册API的详情，只有注册API返回。","type":"object","properties":{"ServiceHost":{"description":"后端服务地址","type":"string","example":"http://example.aliyundoc.com"},"ServiceContentType":{"description":"API返回数据类型，可选枚举值：\n\n- 0：JSON\n- 1：XML\n\n向导和脚本API只支持JSON；注册API支持JSON和XML。","type":"integer","format":"int32","example":"0"},"ServicePath":{"description":"后端服务路径","type":"string","example":"/index"},"SuccessfulResultSample":{"description":"正常返回示例","type":"string","example":"{\"success\": true}"},"FailedResultSample":{"description":"错误返回示例。","type":"string","example":"{\"success\": false}"},"ServiceRequestBodyDescription":{"description":"后端请求body内容描述","type":"string","example":"{\"abc\":1}"},"RegistrationErrorCodes":{"description":"注册API的错误码列表。","type":"array","items":{"description":"返回对象","type":"object","properties":{"ErrorMessage":{"description":"错误信息。","type":"string","example":"fail to call"},"ErrorCode":{"description":"错误码。","type":"string","example":"1001"},"ErrorSolution":{"description":"错误解决方案。","type":"string","example":"retry"}}}},"RegistrationRequestParameters":{"description":"注册API的请求参数列表。","type":"array","items":{"description":"返回对象","type":"object","properties":{"ColumnName":{"description":"绑定的表字段名称，仅向导模式支持。","type":"string","example":"column1"},"ParameterName":{"description":"参数的名称。","type":"string","example":"name1"},"ParameterPosition":{"description":"参数位置，可选枚举值有：\n\n- 0：Path\n- 1：Query\n- 2：Head\n- 3：Body\n\n向导和脚本API，只支持Query；注册API，GET、DELETE方法支持Query、Head，PUT、POST方法支持Query、Head、Body。","type":"integer","format":"int32","example":"0"},"ParameterDescription":{"description":"描述信息。","type":"string","example":"description1"},"DefaultValue":{"description":"默认值。","type":"string","example":"default1"},"ParameterOperator":{"description":"运算符，可选枚举值有：\n\n- 0：Equal\n- 1：Like\n- 2：Const\n- 3：In\n\n向导API支持Equal、Like、In；脚本API支持Equal；注册API支持Equal、Const。","type":"integer","format":"int32","example":"0"},"ParameterDataType":{"description":"数据类型，可选枚举值：\n\n- 0：String\n- 1：Int\n- 2：Long\n- 3：Float\n- 4：Double\n- 5：Boolean\n- 6：StringList\n- 7：IntList\n- 8：LongList\n- 9：FloatList\n- 10：DoubleList\n- 11：BooleanList","type":"integer","format":"int32","example":"0"},"ExampleValue":{"description":"示例值。","type":"string","example":"example1"},"IsRequiredParameter":{"description":"是否必填。","type":"boolean","example":"true"}}}}}},"ScriptDetails":{"description":"脚本API的详情，只有脚本API返回。","type":"object","properties":{"Script":{"description":"SQL脚本。","type":"string","example":"select a from t"},"IsPagedResponse":{"description":"返回是否分页。","type":"boolean","example":"true"},"ScriptRequestParameters":{"description":"脚本API的请求参数列表。","type":"array","items":{"description":"返回对象","type":"object","properties":{"ColumnName":{"description":"绑定的表字段名称，仅向导模式支持。","type":"string","example":"column1"},"ParameterName":{"description":"参数的名称。","type":"string","example":"param1"},"ParameterPosition":{"description":"参数的位置，可选枚举值包括0（Path）、1（Query）、2（Head）和3（Body）。向导和脚本API仅支持Query。注册API中的GET、DELETE方法支持Query、Head，PUT、POST方法支持Query、Head和Body。","type":"integer","format":"int32","example":"0"},"ParameterDescription":{"description":"描述信息。","type":"string","example":"description1"},"DefaultValue":{"description":"默认值。","type":"string","example":"default1"},"ParameterOperator":{"description":"运算符，可选枚举值包括0（Equal）、1（Like）、2（Const）和3（In）。向导模式API支持Equal、Like和In，脚本模式API支持Equal，注册API支持Equal和Const。","type":"integer","format":"int32","example":"0"},"ParameterDataType":{"description":"数据类型，可选枚举值：\n- 0：String\n- 1：Int\n- 2：Long\n- 3：Float\n- 4：Double\n- 5：Boolean\n- 6：StringList\n- 7：IntList\n- 8：LongList\n- 9：FloatList\n- 10：DoubleList\n- 11：BooleanList","type":"integer","format":"int32","example":"0"},"ExampleValue":{"description":"示例值。","type":"string","example":"example1"},"IsRequiredParameter":{"description":"是否必填。","type":"boolean","example":"true"}}}},"ScriptResponseParameters":{"description":"脚本API的返回参数列表。","type":"array","items":{"description":"返回对象","type":"object","properties":{"ParameterDescription":{"description":"描述信息。","type":"string","example":"description2"},"ColumnName":{"description":"绑定的表字段名称，仅向导模式支持。","type":"string","example":"column2"},"ParameterName":{"description":"参数的名称。","type":"string","example":"param2"},"ParameterDataType":{"description":"数据类型，可选枚举值：\n\n- 0：String\n- 1：Int\n- 2：Long\n- 3：Float\n- 4：Double\n- 5：Boolean\n- 6：StringList\n- 7：IntList\n- 8：LongList\n- 9：FloatList\n- 10：DoubleList\n- 11：BooleanList","type":"integer","format":"int32","example":"0"},"ExampleValue":{"description":"示例值。","type":"string","example":"example2"}}}},"ScriptConnection":{"description":"脚本API的数据源信息。","type":"object","properties":{"TableName":{"description":"数据源表的名称。","type":"string","example":"t"},"ConnectionId":{"description":"数据源ID。","type":"integer","format":"int64","example":"123"}}}}},"WizardDetails":{"description":"向导API详情，只有向导API返回。","type":"object","properties":{"IsPagedResponse":{"description":"返回是否分页。","type":"boolean","example":"true"},"WizardRequestParameters":{"description":"向导API的请求参数列表。","type":"array","items":{"description":"返回对象","type":"object","properties":{"ColumnName":{"description":"绑定的表字段名称，仅向导模式支持。","type":"string","example":"column1"},"ParameterName":{"description":"参数的名称。","type":"string","example":"param1"},"ParameterPosition":{"description":"参数的位置，可选枚举值包括0（Path）、1（Query）、2（Head）和3（Body）。向导和脚本API仅支持Query。注册API中的GET、DELETE方法支持Query、Head，PUT、POST方法支持Query、Head和Body。","type":"integer","format":"int32","example":"0"},"ParameterDescription":{"description":"描述信息。","type":"string","example":"description1"},"DefaultValue":{"description":"默认值。","type":"string","example":"default1"},"ParameterOperator":{"description":"运算符，可选枚举值包括0（Equal）、1（Like）、2（Const）和3（In）。向导模式API支持Equal、Like和In，脚本模式API支持Equal，注册API支持Equal和Const。","type":"integer","format":"int32","example":"0"},"ParameterDataType":{"description":"数据类型，可选枚举值：\n\n- 0：String\n- 1：Int\n- 2：Long\n- 3：Float\n- 4：Double\n- 5：Boolean\n- 6：StringList\n- 7：IntList\n- 8：LongList\n- 9：FloatList\n- 10：DoubleList\n- 11：BooleanList","type":"integer","format":"int32","example":"0"},"ExampleValue":{"description":"示例值。","type":"string","example":"example1"},"IsRequiredParameter":{"description":"是否必填。","type":"boolean","example":"true"}}}},"WizardResponseParameters":{"description":"向导模式的返回参数列表。","type":"array","items":{"description":"返回对象","type":"object","properties":{"ParameterDescription":{"description":"描述信息。","type":"string","example":"description2"},"ColumnName":{"description":"绑定的表字段名称，仅向导模式支持。","type":"string","example":"column2"},"ParameterName":{"description":"参数的名称。","type":"string","example":"param2"},"ParameterDataType":{"description":"数据类型，可选枚举值：\n\n- 0：String\n- 1：Int\n- 2：Long\n- 3：Float\n- 4：Double\n- 5：Boolean\n- 6：StringList\n- 7：IntList\n- 8：LongList\n- 9：FloatList\n- 10：DoubleList\n- 11：BooleanList","type":"integer","format":"int32","example":"0"},"ExampleValue":{"description":"示例值。","type":"string","example":"example2"}}}},"WizardConnection":{"description":"向导API的数据源信息。","type":"object","properties":{"TableName":{"description":"数据源的表名称。","type":"string","example":"t"},"ConnectionId":{"description":"数据源ID。","type":"integer","format":"int64","example":"123"}}}}}}}}}}},"errorCodes":{"403":[{"errorCode":"Forbidden.Access","errorMessage":"Access is forbidden. Please first activate DataWorks Enterprise Edition or Flagship Edition."}],"429":[{"errorCode":"Throttling.Api","errorMessage":"The request for this resource has exceeded your available limit."},{"errorCode":"Throttling.System","errorMessage":"The DataWorks system is busy. Try again later."},{"errorCode":"Throttling.User","errorMessage":"Your request is too frequent. Try again later."}],"500":[{"errorCode":"InternalError.System","errorMessage":"An internal system error occurred. Try again later."},{"errorCode":"InternalError.UserId.Missing","errorMessage":"An internal system error occurred. Try again later."}]},"responseDemo":"[{\"type\":\"json\",\"example\":\"{\\n  \\\"HttpStatusCode\\\": 200,\\n  \\\"RequestId\\\": \\\"0000-ABCD-EFG****\\\",\\n  \\\"ErrorMessage\\\": \\\"The specified parameters are invalid.\\\",\\n  \\\"Success\\\": true,\\n  \\\"ErrorCode\\\": \\\"1031203110005\\\",\\n  \\\"Data\\\": {\\n    \\\"Timeout\\\": 10000,\\n    \\\"Status\\\": 0,\\n    \\\"ApiId\\\": 10000,\\n    \\\"ApiMode\\\": 0,\\n    \\\"ProjectId\\\": 10001,\\n    \\\"ResponseContentType\\\": 0,\\n    \\\"CreatorId\\\": \\\"1234567\\\",\\n    \\\"VisibleRange\\\": 0,\\n    \\\"ModifiedTime\\\": \\\"2020-06-23T00:21:01+0800\\\",\\n    \\\"OperatorId\\\": \\\"2345678\\\",\\n    \\\"GroupId\\\": \\\"ab123****\\\",\\n    \\\"Description\\\": \\\"测试API描述\\\",\\n    \\\"FolderId\\\": 0,\\n    \\\"RequestMethod\\\": 0,\\n    \\\"CreatedTime\\\": \\\"2020-06-23T00:21:01+0800\\\",\\n    \\\"ApiName\\\": \\\"测试API名称\\\",\\n    \\\"TenantId\\\": 10002,\\n    \\\"ApiPath\\\": \\\"/test/1\\\",\\n    \\\"Protocols\\\": [\\n      0\\n    ],\\n    \\\"RegistrationDetails\\\": {\\n      \\\"ServiceHost\\\": \\\"http://example.aliyundoc.com\\\",\\n      \\\"ServiceContentType\\\": 0,\\n      \\\"ServicePath\\\": \\\"/index\\\",\\n      \\\"SuccessfulResultSample\\\": \\\"{\\\\\\\"success\\\\\\\": true}\\\",\\n      \\\"FailedResultSample\\\": \\\"{\\\\\\\"success\\\\\\\": false}\\\",\\n      \\\"ServiceRequestBodyDescription\\\": \\\"{\\\\\\\"abc\\\\\\\":1}\\\",\\n      \\\"RegistrationErrorCodes\\\": [\\n        {\\n          \\\"ErrorMessage\\\": \\\"fail to call\\\",\\n          \\\"ErrorCode\\\": \\\"1001\\\",\\n          \\\"ErrorSolution\\\": \\\"retry\\\"\\n        }\\n      ],\\n      \\\"RegistrationRequestParameters\\\": [\\n        {\\n          \\\"ColumnName\\\": \\\"column1\\\",\\n          \\\"ParameterName\\\": \\\"name1\\\",\\n          \\\"ParameterPosition\\\": 0,\\n          \\\"ParameterDescription\\\": \\\"description1\\\",\\n          \\\"DefaultValue\\\": \\\"default1\\\",\\n          \\\"ParameterOperator\\\": 0,\\n          \\\"ParameterDataType\\\": 0,\\n          \\\"ExampleValue\\\": \\\"example1\\\",\\n          \\\"IsRequiredParameter\\\": true\\n        }\\n      ]\\n    },\\n    \\\"ScriptDetails\\\": {\\n      \\\"Script\\\": \\\"select a from t\\\",\\n      \\\"IsPagedResponse\\\": true,\\n      \\\"ScriptRequestParameters\\\": [\\n        {\\n          \\\"ColumnName\\\": \\\"column1\\\",\\n          \\\"ParameterName\\\": \\\"param1\\\",\\n          \\\"ParameterPosition\\\": 0,\\n          \\\"ParameterDescription\\\": \\\"description1\\\",\\n          \\\"DefaultValue\\\": \\\"default1\\\",\\n          \\\"ParameterOperator\\\": 0,\\n          \\\"ParameterDataType\\\": 0,\\n          \\\"ExampleValue\\\": \\\"example1\\\",\\n          \\\"IsRequiredParameter\\\": true\\n        }\\n      ],\\n      \\\"ScriptResponseParameters\\\": [\\n        {\\n          \\\"ParameterDescription\\\": \\\"description2\\\",\\n          \\\"ColumnName\\\": \\\"column2\\\",\\n          \\\"ParameterName\\\": \\\"param2\\\",\\n          \\\"ParameterDataType\\\": 0,\\n          \\\"ExampleValue\\\": \\\"example2\\\"\\n        }\\n      ],\\n      \\\"ScriptConnection\\\": {\\n        \\\"TableName\\\": \\\"t\\\",\\n        \\\"ConnectionId\\\": 123\\n      }\\n    },\\n    \\\"WizardDetails\\\": {\\n      \\\"IsPagedResponse\\\": true,\\n      \\\"WizardRequestParameters\\\": [\\n        {\\n          \\\"ColumnName\\\": \\\"column1\\\",\\n          \\\"ParameterName\\\": \\\"param1\\\",\\n          \\\"ParameterPosition\\\": 0,\\n          \\\"ParameterDescription\\\": \\\"description1\\\",\\n          \\\"DefaultValue\\\": \\\"default1\\\",\\n          \\\"ParameterOperator\\\": 0,\\n          \\\"ParameterDataType\\\": 0,\\n          \\\"ExampleValue\\\": \\\"example1\\\",\\n          \\\"IsRequiredParameter\\\": true\\n        }\\n      ],\\n      \\\"WizardResponseParameters\\\": [\\n        {\\n          \\\"ParameterDescription\\\": \\\"description2\\\",\\n          \\\"ColumnName\\\": \\\"column2\\\",\\n          \\\"ParameterName\\\": \\\"param2\\\",\\n          \\\"ParameterDataType\\\": 0,\\n          \\\"ExampleValue\\\": \\\"example2\\\"\\n        }\\n      ],\\n      \\\"WizardConnection\\\": {\\n        \\\"TableName\\\": \\\"t\\\",\\n        \\\"ConnectionId\\\": 123\\n      }\\n    }\\n  }\\n}\",\"errorExample\":\"\"},{\"type\":\"xml\",\"example\":\"<GetDataServiceApiResponse>\\n    <HttpStatusCode>200</HttpStatusCode>\\n    <RequestId>0000-ABCD-EFG****</RequestId>\\n    <ErrorMessage>The specified parameters are invalid.</ErrorMessage>\\n    <Success>true</Success>\\n    <ErrorCode>1031203110005</ErrorCode>\\n    <Data>\\n        <Timeout>10000</Timeout>\\n        <Status>0</Status>\\n        <ApiId>10000</ApiId>\\n        <ApiMode>0</ApiMode>\\n        <ProjectId>10001</ProjectId>\\n        <ResponseContentType>0</ResponseContentType>\\n        <CreatorId>1234567</CreatorId>\\n        <VisibleRange>0</VisibleRange>\\n        <ModifiedTime>2020-06-23T00:21:01+0800</ModifiedTime>\\n        <OperatorId>2345678</OperatorId>\\n        <GroupId>ab123****</GroupId>\\n        <Description>测试API描述</Description>\\n        <FolderId>0</FolderId>\\n        <RequestMethod>0</RequestMethod>\\n        <CreatedTime>2020-06-23T00:21:01+0800</CreatedTime>\\n        <ApiName>测试API名称</ApiName>\\n        <TenantId>10002</TenantId>\\n        <ApiPath>/test/1</ApiPath>\\n        <Protocols>0</Protocols>\\n        <RegistrationDetails>\\n            <ServiceHost>http://example.aliyundoc.com</ServiceHost>\\n            <ServiceContentType>0</ServiceContentType>\\n            <ServicePath>/index</ServicePath>\\n            <SuccessfulResultSample>{\\\"success\\\": true}</SuccessfulResultSample>\\n            <FailedResultSample>{\\\"success\\\": false}</FailedResultSample>\\n            <ServiceRequestBodyDescription>{\\\"abc\\\":1}</ServiceRequestBodyDescription>\\n            <RegistrationErrorCodes>\\n                <ErrorMessage>fail to call</ErrorMessage>\\n                <ErrorCode>1001</ErrorCode>\\n                <ErrorSolution>retry</ErrorSolution>\\n            </RegistrationErrorCodes>\\n            <RegistrationRequestParameters>\\n                <ColumnName>column1</ColumnName>\\n                <ParameterName>name1</ParameterName>\\n                <ParameterPosition>0</ParameterPosition>\\n                <ParameterDescription>description1</ParameterDescription>\\n                <DefaultValue>default1</DefaultValue>\\n                <ParameterOperator>0</ParameterOperator>\\n                <ParameterDataType>0</ParameterDataType>\\n                <ExampleValue>example1</ExampleValue>\\n                <IsRequiredParameter>true</IsRequiredParameter>\\n            </RegistrationRequestParameters>\\n        </RegistrationDetails>\\n        <ScriptDetails>\\n            <Script>select a from t</Script>\\n            <IsPagedResponse>true</IsPagedResponse>\\n            <ScriptRequestParameters>\\n                <ColumnName>column1</ColumnName>\\n                <ParameterName>param1</ParameterName>\\n                <ParameterPosition>0</ParameterPosition>\\n                <ParameterDescription>description1</ParameterDescription>\\n                <DefaultValue>default1</DefaultValue>\\n                <ParameterOperator>0</ParameterOperator>\\n                <ParameterDataType>0</ParameterDataType>\\n                <ExampleValue>example1</ExampleValue>\\n                <IsRequiredParameter>true</IsRequiredParameter>\\n            </ScriptRequestParameters>\\n            <ScriptResponseParameters>\\n                <ParameterDescription>description2</ParameterDescription>\\n                <ColumnName>column2</ColumnName>\\n                <ParameterName>param2</ParameterName>\\n                <ParameterDataType>0</ParameterDataType>\\n                <ExampleValue>example2</ExampleValue>\\n            </ScriptResponseParameters>\\n            <ScriptConnection>\\n                <TableName>t</TableName>\\n                <ConnectionId>123</ConnectionId>\\n            </ScriptConnection>\\n        </ScriptDetails>\\n        <WizardDetails>\\n            <IsPagedResponse>true</IsPagedResponse>\\n            <WizardRequestParameters>\\n                <ColumnName>column1</ColumnName>\\n                <ParameterName>param1</ParameterName>\\n                <ParameterPosition>0</ParameterPosition>\\n                <ParameterDescription>description1</ParameterDescription>\\n                <DefaultValue>default1</DefaultValue>\\n                <ParameterOperator>0</ParameterOperator>\\n                <ParameterDataType>0</ParameterDataType>\\n                <ExampleValue>example1</ExampleValue>\\n                <IsRequiredParameter>true</IsRequiredParameter>\\n            </WizardRequestParameters>\\n            <WizardResponseParameters>\\n                <ParameterDescription>description2</ParameterDescription>\\n                <ColumnName>column2</ColumnName>\\n                <ParameterName>param2</ParameterName>\\n                <ParameterDataType>0</ParameterDataType>\\n                <ExampleValue>example2</ExampleValue>\\n            </WizardResponseParameters>\\n            <WizardConnection>\\n                <TableName>t</TableName>\\n                <ConnectionId>123</ConnectionId>\\n            </WizardConnection>\\n        </WizardDetails>\\n    </Data>\\n</GetDataServiceApiResponse>\",\"errorExample\":\"\"}]","title":"查询数据服务API开发态的详情","summary":"调用GetDataServiceApi查询数据服务API开发态的详情。","requestParamsDescription":" ","responseParamsDescription":" 不同类型API的详情信息通过不同字段返回。向导API使用WizardDetails字段，脚本API使用ScriptDetails字段，注册API使用RegistrationDetails字段。","extraInfo":" "}