{"summary":"同步执行产品操作功能。","methods":["post","get"],"schemes":["http","https"],"security":[{"AK":[]}],"operationType":"read","deprecated":false,"systemTags":{},"parameters":[{"name":"ApplicationId","in":"formData","schema":{"title":"云速搭应用ID","description":"云速搭应用ID","type":"string","required":false,"example":"BE68D71ZY5YYIU9R"}},{"name":"ServiceType","in":"formData","schema":{"title":"资源类型，如果需要修改 dds 的相关参数请填写：dds。","description":"资源类型，如果需要修改 dds 的相关参数请填写：dds。","type":"string","required":true,"enumValueTitles":{"dds":"dds","ecs":"ecs"},"example":"dds"}},{"name":"Operation","in":"formData","schema":{"title":"本次操作类型","description":"本次操作类型","type":"string","required":true,"enumValueTitles":{"modifyConnectionString":"modifyConnectionString","rename":"rename"},"example":"rename"}},{"name":"Attributes","in":"formData","style":"json","schema":{"title":"操作相关参数，根据不同的Operation值，输入对应的参数","description":"操作相关参数，根据不同的Operation值，输入对应的参数","type":"object","required":false,"additionalProperties":{"type":"any","description":"调试时请先选择“参数类型”，再输入参数值。","example":"选择string类型:”CADT“； 选择number类型:123"}}},{"name":"ResourceGroupId","in":"formData","schema":{"title":"资源组ID，用于资源组权限校验","description":"资源组ID，用于资源组权限校验","type":"string","required":false,"example":"rg-acfmyjt3c5om3hi"}},{"name":"ClientToken","in":"formData","schema":{"title":"幂等标记","description":"幂等标记","type":"string","required":false,"example":"1600765710019"}}],"responses":{"200":{"schema":{"type":"object","properties":{"Message":{"title":"错误信息","description":"错误信息","type":"string","example":"Access key ID cannot be null."},"RequestId":{"title":"请求ID","description":"请求ID","type":"string","example":"FDC73B05-5331-57AA-BA93-4C9882792FF5"},"Data":{"title":"同步操作任务ID","description":"同步操作任务ID","type":"string","example":"op_xxxxxxxxxxxxxxxxxx_dds_modifyInstanceType_BYSOQGWUV6PME412_ERMEZLXNN3K9N3OL"},"Code":{"title":"结果码，200代表成功；其它代表失败。","description":"结果码，200代表成功；其它代表失败。","type":"integer","format":"int32","example":"200"}}}}},"staticInfo":{"returnType":"synchronous"},"responseDemo":"[{\"errorExample\":\"\",\"example\":\"{\\n  \\\"Message\\\": \\\"Access key ID cannot be null.\\\",\\n  \\\"RequestId\\\": \\\"FDC73B05-5331-57AA-BA93-4C9882792FF5\\\",\\n  \\\"Data\\\": \\\"op_xxxxxxxxxxxxxxxxxx_dds_modifyInstanceType_BYSOQGWUV6PME412_ERMEZLXNN3K9N3OL\\\",\\n  \\\"Code\\\": 200\\n}\",\"type\":\"json\"}]","title":"同步执行操作","description":"同步执行产品操作功能。"}