{"summary":"调用ListCustomRoutingPortMappingsByDestination接口查询指定后端实例的端口映射表（自定义路由类型监听）。","methods":["post","get"],"schemes":["http","https"],"security":[{"AK":[]}],"operationType":"read","deprecated":false,"systemTags":{"operationType":"list","riskType":"none","chargeType":"free"},"parameters":[{"name":"RegionId","in":"query","schema":{"description":"全球加速实例所在的地域ID，仅取值**cn-hangzhou**。","type":"string","required":true,"example":"cn-hangzhou"}},{"name":"PageNumber","in":"query","schema":{"description":"列表的页码，默认值：**1**。","type":"integer","format":"int32","required":false,"minimum":"1","example":"1","default":"1"}},{"name":"PageSize","in":"query","schema":{"description":"分页查询时每页的条目数。最大值：**50**。默认值：**10**。","type":"integer","format":"int32","required":false,"maximum":"50","minimum":"1","example":"10","default":"10"}},{"name":"EndpointId","in":"query","schema":{"description":"待查询后端实例所属的终端节点ID。","type":"string","required":true,"example":"ep-bp16jdc00bhe97sr5****"}},{"name":"DestinationAddress","in":"query","schema":{"description":"待查询后端实例服务IP地址。","type":"string","required":true,"example":"10.0.XX.XX"}}],"responses":{"200":{"schema":{"title":"Schema of Response","description":"返回信息列表。","type":"object","properties":{"RequestId":{"title":"Id of the request","description":"请求ID。","type":"string","example":"String\t04F0F334-1335-436C-A1D7-6C044FE73368"},"TotalCount":{"description":"列表条目数。","type":"integer","format":"int32","example":"1"},"PageSize":{"description":"分页查询时每页的条目数。","type":"integer","format":"int32","example":"10"},"PageNumber":{"description":"列表的页码。","type":"integer","format":"int32","example":"1"},"PortMappings":{"description":"端口映射表信息。","type":"array","items":{"description":"端口映射表信息。","type":"object","properties":{"AcceleratorId":{"description":"端口映射表所属全球加速实例ID。","type":"string","example":"ga-bp1odcab8tmno0hdq****"},"ListenerId":{"description":"端口映射表所属自定义路由类型监听ID。","type":"string","example":"ga-bp1odcab8tmno0hdq****"},"EndpointGroupId":{"description":"终端节点组ID。","type":"string","example":"epg-bp14sz7ftcwwjgrdm****"},"EndpointId":{"description":"终端节点ID。","type":"string","example":"ep-bp14sz7ftcwwjgrdm****"},"EndpointGroupRegion":{"description":"终端节点组所属地域ID。","type":"string","example":"us-west-1"},"Vswitch":{"description":"终端节点交换机（vSwitch）实例名称。","type":"string","example":"vsw-test01"},"AcceleratorPort":{"description":"加速端口。","type":"integer","format":"int32","example":"3000"},"Protocols":{"description":"后端服务协议类型。\n- **TCP**：TCP协议。\n- **UDP**：UDP协议。","type":"array","items":{"description":"后端服务协议类型。\n- **TCP**：TCP协议。\n- **UDP**：UDP协议。","type":"string","example":"TCP"}},"DestinationTrafficState":{"description":"后端实例流量通行策略。\n\n- **allow**：允许后端实例接收流量。\n\n- **deny**：不允许后端实例接收流量。","type":"string","example":"allow"},"DestinationSocketAddress":{"description":"后端实例服务IP地址与端口信息。","type":"object","properties":{"IpAddress":{"description":"后端实例服务IP地址。","type":"string","example":"10.0.XX.XX"},"Port":{"description":"后端实例服务端口。","type":"integer","format":"int32","example":"443"}}}}}}}}}},"responseDemo":"[{\"type\":\"json\",\"example\":\"{\\n  \\\"RequestId\\\": \\\"String\\\\t04F0F334-1335-436C-A1D7-6C044FE73368\\\",\\n  \\\"TotalCount\\\": 1,\\n  \\\"PageSize\\\": 10,\\n  \\\"PageNumber\\\": 1,\\n  \\\"PortMappings\\\": [\\n    {\\n      \\\"AcceleratorId\\\": \\\"ga-bp1odcab8tmno0hdq****\\\",\\n      \\\"ListenerId\\\": \\\"ga-bp1odcab8tmno0hdq****\\\",\\n      \\\"EndpointGroupId\\\": \\\"epg-bp14sz7ftcwwjgrdm****\\\",\\n      \\\"EndpointId\\\": \\\"ep-bp14sz7ftcwwjgrdm****\\\",\\n      \\\"EndpointGroupRegion\\\": \\\"us-west-1\\\",\\n      \\\"Vswitch\\\": \\\"vsw-test01\\\",\\n      \\\"AcceleratorPort\\\": 3000,\\n      \\\"Protocols\\\": [\\n        \\\"TCP\\\"\\n      ],\\n      \\\"DestinationTrafficState\\\": \\\"allow\\\",\\n      \\\"DestinationSocketAddress\\\": {\\n        \\\"IpAddress\\\": \\\"10.0.XX.XX\\\",\\n        \\\"Port\\\": 443\\n      }\\n    }\\n  ]\\n}\",\"errorExample\":\"\"},{\"type\":\"xml\",\"example\":\"<ListCustomRoutingPortMappingsByDestinationResponse>\\n    <RequestId>String\\t04F0F334-1335-436C-A1D7-6C044FE73368</RequestId>\\n    <TotalCount>1</TotalCount>\\n    <PageSize>10</PageSize>\\n    <PageNumber>1</PageNumber>\\n    <PortMappings>\\n        <AcceleratorId>ga-bp1odcab8tmno0hdq****</AcceleratorId>\\n        <ListenerId>ga-bp1odcab8tmno0hdq****</ListenerId>\\n        <EndpointGroupId>epg-bp14sz7ftcwwjgrdm****</EndpointGroupId>\\n        <EndpointId>ep-bp14sz7ftcwwjgrdm****</EndpointId>\\n        <EndpointGroupRegion>us-west-1</EndpointGroupRegion>\\n        <Vswitch>vsw-test01</Vswitch>\\n        <AcceleratorPort>3000</AcceleratorPort>\\n        <Protocols>TCP</Protocols>\\n        <DestinationTrafficState>allow</DestinationTrafficState>\\n        <DestinationSocketAddress>\\n            <IpAddress>10.0.XX.XX</IpAddress>\\n            <Port>443</Port>\\n        </DestinationSocketAddress>\\n    </PortMappings>\\n</ListCustomRoutingPortMappingsByDestinationResponse>\",\"errorExample\":\"\"}]","title":"查询指定后端实例的端口映射表"}