{"summary":"查询一个EIAM组织信息。","methods":["get","post"],"schemes":["https"],"security":[{"AK":[]}],"operationType":"read","deprecated":false,"systemTags":{"operationType":"get"},"parameters":[{"name":"InstanceId","in":"query","schema":{"title":"实例ID。","description":"实例ID。","type":"string","required":true,"example":"idaas_ue2jvisn35ea5lmthk267xxxxx","maxLength":64}},{"name":"OrganizationalUnitId","in":"query","schema":{"title":"组织ID。","description":"组织ID。","type":"string","required":true,"example":"ou_wovwffm62xifdziem7an7xxxxx","maxLength":64}}],"responses":{"200":{"schema":{"description":"响应结果。","type":"object","properties":{"RequestId":{"title":"请求ID。","description":"请求ID。","type":"string","example":"0441BD79-92F3-53AA-8657-F8CE4A2B912A"},"OrganizationalUnit":{"description":"组织数据对象。","type":"object","properties":{"OrganizationalUnitId":{"title":"机构ID","description":"组织ID。","type":"string","example":"ou_wovwffm62xifdziem7an7xxxxx"},"OrganizationalUnitName":{"title":"机构名称","description":"组织名称。","type":"string","example":"test_organizationalUnit_name"},"ParentId":{"title":"父机构ID","description":"父组织ID。","type":"string","example":"ou_wovwffm62xifdziem7an7xxxxx"},"OrganizationalUnitExternalId":{"title":"外部ID","description":"组织外部ID，用于外部数据与IDaaS组织的数据关联映射，默认为IDaaS组织ID。\n\n说明：外部ID在同一来源类型和来源ID下唯一。","type":"string","example":"ou_wovwffm62xifdziem7an7xxxxx"},"OrganizationalUnitSourceType":{"title":"来源类型","description":"账户来源类型，取值可选范围：\n- build\\_in：自建。\n- ding\\_talk：钉钉导入。\n- ad：AD导入。\n- ldap：LDAP导入。\n- we\\_com：企业微信导入。","type":"string","example":"build_in"},"OrganizationalUnitSourceId":{"title":"来源ID","description":"组织来源ID。\n\n自建类型默认为实例ID，其他类型，分别对应不同来源的企业ID，比如钉钉来源对应钉钉企业的corpId。","type":"string","example":"idaas_ue2jvisn35ea5lmthk267xxxxx"},"CreateTime":{"title":"创建时间","description":"组织创建时间，Unix时间戳格式，单位为毫秒。","type":"integer","format":"int64","example":"1652085686179"},"UpdateTime":{"title":"最近一次更新时间","description":"最近一次更新时间，Unix时间戳格式，单位为毫秒。","type":"integer","format":"int64","example":"1652085686179"},"Description":{"title":"描述","description":"组织描述信息。","type":"string","example":"测试组织"},"InstanceId":{"title":"实例ID","description":"实例ID。","type":"string","example":"idaas_ue2jvisn35ea5lmthk267xxxxx"},"Leaf":{"title":"是否叶子节点","description":"是否叶子节点，true表示该组织没有子节点，false表示该组织下存在子节点。","type":"boolean","example":"false"}}}}}}},"responseDemo":"[{\"errorExample\":\"\",\"example\":\"{\\n  \\\"RequestId\\\": \\\"0441BD79-92F3-53AA-8657-F8CE4A2B912A\\\",\\n  \\\"OrganizationalUnit\\\": {\\n    \\\"OrganizationalUnitId\\\": \\\"ou_wovwffm62xifdziem7an7xxxxx\\\",\\n    \\\"OrganizationalUnitName\\\": \\\"test_organizationalUnit_name\\\",\\n    \\\"ParentId\\\": \\\"ou_wovwffm62xifdziem7an7xxxxx\\\",\\n    \\\"OrganizationalUnitExternalId\\\": \\\"ou_wovwffm62xifdziem7an7xxxxx\\\",\\n    \\\"OrganizationalUnitSourceType\\\": \\\"build_in\\\",\\n    \\\"OrganizationalUnitSourceId\\\": \\\"idaas_ue2jvisn35ea5lmthk267xxxxx\\\",\\n    \\\"CreateTime\\\": 1652085686179,\\n    \\\"UpdateTime\\\": 1652085686179,\\n    \\\"Description\\\": \\\"测试组织\\\",\\n    \\\"InstanceId\\\": \\\"idaas_ue2jvisn35ea5lmthk267xxxxx\\\",\\n    \\\"Leaf\\\": false\\n  }\\n}\",\"type\":\"json\"}]","title":"查询一个EIAM组织信息"}